qval/__init__.py
qval/exceptions.py
qval/framework_integration.py
qval/qval.py
qval/utils.py
qval/validator.py
qval-0.4.2.dist-info/LICENSE
qval-0.4.2.dist-info/WHEEL
qval-0.4.2.dist-info/METADATA
qval-0.4.2.dist-info/RECORD
