Metadata-Version: 2.1
Name: qval
Version: 0.4.2
Summary: This module provides a convenient API for verifying query parameters.
Home-page: https://github.com/OptimalStrategy/Qval
License: UNKNOWN
Author: George Usan-Podgornov
Author-email: 
Classifier: License :: OSI Approved :: MIT License
